pysamloader_gui/__init__.py
pysamloader_gui/_version.py
pysamloader_gui/app.py
pysamloader_gui/widgets.py
pysamloader_gui/assets/binary.png
pysamloader_gui/assets/connectors.png
pysamloader_gui/assets/finish.png
pysamloader_gui/assets/icon.ico
pysamloader_gui/assets/icon.png
pysamloader_gui/assets/icon.xcf
pysamloader_gui/assets/info.png
pysamloader_gui/assets/logo-full.png
pysamloader_gui/assets/sam-ic.png
pysamloader_gui/assets/verify.png
pysamloader_gui/assets/write.png
pysamloader_gui-0.6.5.dist-info/LICENSE
pysamloader_gui-0.6.5.dist-info/METADATA
pysamloader_gui-0.6.5.dist-info/WHEEL
pysamloader_gui-0.6.5.dist-info/entry_points.txt
pysamloader_gui-0.6.5.dist-info/top_level.txt
pysamloader_gui-0.6.5.dist-info/RECORD
