Metadata-Version: 2.1
Name: pysamloader-gui
Version: 0.6.5
Summary: Kivy GUI for pysamloader
Home-page: https://github.com/ebs-universe/pysamloader-gui
Author: Chintalagiri Shashank
Author-email: shashank@chintal.in
License: UNKNOWN
Project-URL: Source Repository, https://github.com/ebs-universe/pysamloader-gui/
Project-URL: Documentation, https://pysamloader-gui.readthedocs.io/en/latest/index.html
Project-URL: Issue Tracker, https://github.com/ebs-universe/pysamloader-gui/issues
Keywords: utilities
Platform: any
Classifier: Development Status :: 3 - Alpha
Classifier: Topic :: Software Development :: Embedded Systems
Classifier: License :: OSI Approved :: GNU General Public License v3 or later (GPLv3+)
Classifier: Programming Language :: Python
Classifier: Intended Audience :: Developers
Classifier: Natural Language :: English
Classifier: Operating System :: OS Independent
Classifier: Environment :: Console
Classifier: Programming Language :: Python
Classifier: Programming Language :: Python :: 3
Classifier: Programming Language :: Python :: 3.5
Classifier: Programming Language :: Python :: 3.6
Classifier: Programming Language :: Python :: 3.7
Classifier: Programming Language :: Python :: Implementation :: CPython
Classifier: Programming Language :: Python :: Implementation :: PyPy
Requires-Python: >=3.4
Requires-Dist: pysamloader
Requires-Dist: cython
Requires-Dist: kivy
Requires-Dist: wheel
Provides-Extra: build
Requires-Dist: setuptools-scm ; extra == 'build'
Requires-Dist: sphinx ; extra == 'build'
Requires-Dist: sphinx-argparse ; extra == 'build'
Requires-Dist: sphinxcontrib-documentedlist ; extra == 'build'
Requires-Dist: alabaster ; extra == 'build'
Requires-Dist: pytest ; extra == 'build'
Requires-Dist: pytest-cov ; extra == 'build'
Requires-Dist: coveralls[yaml] ; extra == 'build'
Requires-Dist: doit ; extra == 'build'
Requires-Dist: pyinstaller ; extra == 'build'
Provides-Extra: dev
Requires-Dist: setuptools-scm ; extra == 'dev'
Requires-Dist: sphinx ; extra == 'dev'
Requires-Dist: sphinx-argparse ; extra == 'dev'
Requires-Dist: sphinxcontrib-documentedlist ; extra == 'dev'
Requires-Dist: alabaster ; extra == 'dev'
Requires-Dist: pytest ; extra == 'dev'
Requires-Dist: pytest-cov ; extra == 'dev'
Requires-Dist: coveralls[yaml] ; extra == 'dev'
Requires-Dist: doit ; extra == 'dev'
Requires-Dist: pyinstaller ; extra == 'dev'
Provides-Extra: docs
Requires-Dist: setuptools-scm ; extra == 'docs'
Requires-Dist: sphinx ; extra == 'docs'
Requires-Dist: sphinx-argparse ; extra == 'docs'
Requires-Dist: sphinxcontrib-documentedlist ; extra == 'docs'
Requires-Dist: alabaster ; extra == 'docs'
Provides-Extra: publish
Requires-Dist: setuptools-scm ; extra == 'publish'
Requires-Dist: sphinx ; extra == 'publish'
Requires-Dist: sphinx-argparse ; extra == 'publish'
Requires-Dist: sphinxcontrib-documentedlist ; extra == 'publish'
Requires-Dist: alabaster ; extra == 'publish'
Requires-Dist: pytest ; extra == 'publish'
Requires-Dist: pytest-cov ; extra == 'publish'
Requires-Dist: coveralls[yaml] ; extra == 'publish'
Requires-Dist: doit ; extra == 'publish'
Requires-Dist: pyinstaller ; extra == 'publish'
Requires-Dist: twine ; extra == 'publish'
Requires-Dist: pygithub ; extra == 'publish'
Provides-Extra: tests
Requires-Dist: setuptools-scm ; extra == 'tests'
Requires-Dist: sphinx ; extra == 'tests'
Requires-Dist: sphinx-argparse ; extra == 'tests'
Requires-Dist: sphinxcontrib-documentedlist ; extra == 'tests'
Requires-Dist: alabaster ; extra == 'tests'
Requires-Dist: pytest ; extra == 'tests'
Requires-Dist: pytest-cov ; extra == 'tests'
Requires-Dist: coveralls[yaml] ; extra == 'tests'
